demo/california_housing_api_demo.py
demo/california_housing_fixed.py
demo/california_housing_gpu.py
demo/m5_forecasting_api_demo.py
demo/mnist_demo.py
demo/organic_sensor_fusion_demo.py
ggnes/__init__.py
ggnes/api_wrappers.py
ggnes/config.py
ggnes/visualization.py
ggnes/aggregations/__init__.py
ggnes/api/mvp.py
ggnes/cli/__init__.py
ggnes/cli/search.py
ggnes/core/__init__.py
ggnes/core/edge.py
ggnes/core/graph.py
ggnes/core/id_manager.py
ggnes/core/node.py
ggnes/core/primitives.py
ggnes/datasets/__init__.py
ggnes/datasets/sensor_fusion.py
ggnes/evolution/__init__.py
ggnes/evolution/adaptive.py
ggnes/evolution/checkpointing.py
ggnes/evolution/coevolution.py
ggnes/evolution/composite_genotype.py
ggnes/evolution/genotype.py
ggnes/evolution/island_model.py
ggnes/evolution/islands.py
ggnes/evolution/metrics.py
ggnes/evolution/multi_objective.py
ggnes/evolution/operators.py
ggnes/evolution/selection.py
ggnes/generation/__init__.py
ggnes/generation/matching.py
ggnes/generation/network_gen.py
ggnes/generation/network_generation.py
ggnes/generation/oscillation.py
ggnes/generation/read_only_view.py
ggnes/generation/rule_engine.py
ggnes/generation/transaction.py
ggnes/hierarchical/__init__.py
ggnes/hierarchical/derivation.py
ggnes/hierarchical/embedding.py
ggnes/hierarchical/matching.py
ggnes/hierarchical/module_spec.py
ggnes/hierarchical/shape_inference.py
ggnes/repair/__init__.py
ggnes/repair/repair.py
ggnes/rules/__init__.py
ggnes/rules/conditions.py
ggnes/rules/pattern_matching.py
ggnes/rules/predicates.py
ggnes/rules/rule.py
ggnes/rules/rule_application.py
ggnes/translation/__init__.py
ggnes/translation/backend_parity.py
ggnes/translation/pytorch.py
ggnes/translation/pytorch_impl.py
ggnes/translation/state_manager.py
ggnes/utils/__init__.py
ggnes/utils/demo_runner.py
ggnes/utils/failure_floor.py
ggnes/utils/observability.py
ggnes/utils/repro_bundle.py
ggnes/utils/rng_manager.py
ggnes/utils/serialization.py
ggnes/utils/uuid_provider.py
ggnes/utils/validation.py
ggnes-0.1.2.dist-info/licenses/LICENSE
ggnes-0.1.2.dist-info/licenses/LICENSE.md
ggnes-0.1.2.dist-info/licenses/NOTICE
ggnes-0.1.2.dist-info/METADATA
ggnes-0.1.2.dist-info/WHEEL
ggnes-0.1.2.dist-info/entry_points.txt
ggnes-0.1.2.dist-info/top_level.txt
ggnes-0.1.2.dist-info/RECORD
