Metadata-Version: 2.4
Name: ggnes
Version: 0.1.2
Summary: Graph Grammar Neuroevolution System (GGNES)
Author: GGNES Authors
License: Apache-2.0
Classifier: Programming Language :: Python :: 3
Classifier: License :: OSI Approved :: Apache Software License
Classifier: Operating System :: OS Independent
Requires-Python: >=3.11
License-File: LICENSE
License-File: LICENSE.md
License-File: NOTICE
Requires-Dist: numpy>=1.24
Requires-Dist: scikit-learn>=1.3
Requires-Dist: torch>=2.5
Requires-Dist: matplotlib>=3.8
Provides-Extra: dev
Requires-Dist: pytest; extra == "dev"
Requires-Dist: pytest-cov; extra == "dev"
Dynamic: license-file
